jank/__init__.py
jank/application.py
jank/camera.py
jank/colliders.py
jank/config.py
jank/entity.py
jank/globals.py
jank/load_animation_sheet.py
jank/state_machine.py
jank/networking/__init__.py
jank/networking/client.py
jank/networking/encoders.py
jank/networking/server.py
jank/renderer/__init__.py
jank/renderer/circle_renderer.py
jank/renderer/html_text_renderer.py
jank/renderer/rect_renderer.py
jank/renderer/renderer.py
jank/renderer/sprite_renderer.py
jank/renderer/text_renderer.py
jank/ui/__init__.py
jank/ui/base.py
jank/ui/button.py
jank/ui/ui_renderer.py
jank-0.1.1.dist-info/LICENSE
jank-0.1.1.dist-info/METADATA
jank-0.1.1.dist-info/WHEEL
jank-0.1.1.dist-info/top_level.txt
jank-0.1.1.dist-info/RECORD
