Metadata-Version: 2.1
Name: jank
Version: 0.1.1
Summary: A game engine using Pyglet and Pymunk.
Home-page: https://github.com/LennyPhoenix/Jank-Engine
Author: LennyPhoenix
Author-email: LennyPhoenixC@gmail.com
License: LICENSE
Platform: UNKNOWN
Classifier: Programming Language :: Python :: 3
Classifier: License :: OSI Approved :: MIT License
Classifier: Operating System :: OS Independent
Requires-Python: >=3.6
Requires-Dist: pyglet
Requires-Dist: pymunk (==5.6.0)
